{"hosting_environment":"development","sandbox_mode":false,"feature_flags":{"pilot_open":{"name":"Pilot open","type":"invariant","active":true},"training_with_a_disability":{"name":"Training with a disability","type":"invariant","active":false},"edit_application":{"name":"Edit application","type":"invariant","active":true},"send_reference_email_via_support":{"name":"Send reference email via support","type":"invariant","active":true},"confirm_course_choice_from_find":{"name":"Confirm course choice from find","type":"invariant","active":false},"send_dfe_sign_in_invitations":{"name":"Send DfE sign in invitations","type":"invariant","active":false},"improved_expired_token_flow":{"name":"Improved expired token flow","type":"invariant","active":false},"work_breaks":{"name":"Work breaks","type":"invariant","active":true},"experimental_api_features":{"name":"Experimental api features","type":"invariant","active":true},"confirm_conditions":{"name":"Confirm conditions","type":"invariant","active":false},"automated_referee_chaser":{"name":"Automated referee chaser","type":"invariant","active":false},"automated_provider_chaser":{"name":"Automated provider chaser","type":"invariant","active":false}}}
